odoo/addons/pos_disable_pricelist_selection/README.rst
odoo/addons/pos_disable_pricelist_selection/__init__.py
odoo/addons/pos_disable_pricelist_selection/__manifest__.py
odoo/addons/pos_disable_pricelist_selection/i18n/it.po
odoo/addons/pos_disable_pricelist_selection/i18n/pos_disable_pricelist_selection.pot
odoo/addons/pos_disable_pricelist_selection/models/__init__.py
odoo/addons/pos_disable_pricelist_selection/models/pos_config.py
odoo/addons/pos_disable_pricelist_selection/readme/CONTEXT.rst
odoo/addons/pos_disable_pricelist_selection/readme/CONTRIBUTORS.rst
odoo/addons/pos_disable_pricelist_selection/readme/DESCRIPTION.rst
odoo/addons/pos_disable_pricelist_selection/readme/HISTORY.rst
odoo/addons/pos_disable_pricelist_selection/readme/USAGE.rst
odoo/addons/pos_disable_pricelist_selection/static/description/icon.png
odoo/addons/pos_disable_pricelist_selection/static/description/index.html
odoo/addons/pos_disable_pricelist_selection/static/src/js/PosModel.js
odoo/addons/pos_disable_pricelist_selection/static/src/js/ProductScreen.js
odoo/addons/pos_disable_pricelist_selection/static/src/js/SetPricelistButton.js
odoo/addons/pos_disable_pricelist_selection/static/src/xml/ClientDetailsEdit.xml
odoo/addons/pos_disable_pricelist_selection/views/assets.xml
odoo/addons/pos_disable_pricelist_selection/views/pos_config_view.xml
odoo14_addon_pos_disable_pricelist_selection-14.0.2.0.0.dist-info/METADATA
odoo14_addon_pos_disable_pricelist_selection-14.0.2.0.0.dist-info/WHEEL
odoo14_addon_pos_disable_pricelist_selection-14.0.2.0.0.dist-info/top_level.txt
odoo14_addon_pos_disable_pricelist_selection-14.0.2.0.0.dist-info/RECORD
